{
  "model_name": "XGBoost",
  "best_overall_score": 0.5542149918556386,
  "best_overall_params": {
    "colsample_bytree": 0.630136081840562,
    "gamma": 0.3440211235296379,
    "learning_rate": 0.5019257201500111,
    "max_depth": 7,
    "min_child_weight": 9,
    "n_estimators": 190,
    "reg_alpha": 0.6653372537974918,
    "reg_lambda": 0.9341479007588223,
    "subsample": 0.8239405984249891
  },
  "search_config": {
    "n_searches": 20,
    "n_iter_per_search": 80,
    "scoring": "f1",
    "cv_folds": 5,
    "total_configurations": 1600
  },
  "top_configs": [
    {
      "mean_test_score": 0.5542149918556386,
      "std_test_score": 0.025242683303832666,
      "n_estimators": 190,
      "max_depth": 7,
      "learning_rate": 0.5019257201500111,
      "subsample": 0.8239405984249891,
      "colsample_bytree": 0.630136081840562,
      "reg_alpha": 0.6653372537974918,
      "reg_lambda": 0.9341479007588223,
      "min_child_weight": 9,
      "gamma": 0.3440211235296379
    },
    {
      "mean_test_score": 0.5473380026914896,
      "std_test_score": 0.020498976036668382,
      "n_estimators": 234,
      "max_depth": 8,
      "learning_rate": 0.6610368123962875,
      "subsample": 0.8096626623048653,
      "colsample_bytree": 0.3779982833424359,
      "reg_alpha": 1.3144867939917249,
      "reg_lambda": 1.0558483768021454,
      "min_child_weight": 8,
      "gamma": 0.187679770741785
    },
    {
      "mean_test_score": 0.5459176237985643,
      "std_test_score": 0.04699871405724838,
      "n_estimators": 311,
      "max_depth": 10,
      "learning_rate": 0.667297350300762,
      "subsample": 0.8640409873535514,
      "colsample_bytree": 0.49322838937090924,
      "reg_alpha": 1.0149937467131518,
      "reg_lambda": 1.724927990736132,
      "min_child_weight": 3,
      "gamma": 0.23317120425941673
    },
    {
      "mean_test_score": 0.5453802121687217,
      "std_test_score": 0.018653769199669396,
      "n_estimators": 215,
      "max_depth": 4,
      "learning_rate": 0.5324343878705475,
      "subsample": 0.8577965241531951,
      "colsample_bytree": 0.25232974249058315,
      "reg_alpha": 1.4241346715004413,
      "reg_lambda": 1.3805396486859796,
      "min_child_weight": 4,
      "gamma": 0.46533249533337884
    },
    {
      "mean_test_score": 0.5445017482840505,
      "std_test_score": 0.02598122551463528,
      "n_estimators": 376,
      "max_depth": 5,
      "learning_rate": 0.6411364385707143,
      "subsample": 0.7814361593585898,
      "colsample_bytree": 0.5122598930454786,
      "reg_alpha": 1.0359887432139778,
      "reg_lambda": 1.1032994630013335,
      "min_child_weight": 4,
      "gamma": 0.2001401493037725
    },
    {
      "mean_test_score": 0.5442370522858138,
      "std_test_score": 0.03779840469750485,
      "n_estimators": 163,
      "max_depth": 10,
      "learning_rate": 0.5386950709152898,
      "subsample": 0.8798253874309709,
      "colsample_bytree": 0.48569941746339984,
      "reg_alpha": 1.27990296041508,
      "reg_lambda": 1.821338644227109,
      "min_child_weight": 4,
      "gamma": 0.37128779933691103
    },
    {
      "mean_test_score": 0.5441157663503471,
      "std_test_score": 0.03512224809422113,
      "n_estimators": 364,
      "max_depth": 8,
      "learning_rate": 0.7625856748742161,
      "subsample": 0.6704240564161046,
      "colsample_bytree": 0.4551857465304453,
      "reg_alpha": 1.0101097314790075,
      "reg_lambda": 1.8204680493048513,
      "min_child_weight": 1,
      "gamma": 0.2124146508979553
    },
    {
      "mean_test_score": 0.5434954515756023,
      "std_test_score": 0.034472396598611406,
      "n_estimators": 315,
      "max_depth": 7,
      "learning_rate": 0.5817601112674406,
      "subsample": 0.8791916367450099,
      "colsample_bytree": 0.592638700214359,
      "reg_alpha": 0.8943530915882241,
      "reg_lambda": 1.9311943502876363,
      "min_child_weight": 12,
      "gamma": 0.20748997929862437
    },
    {
      "mean_test_score": 0.5427691920203133,
      "std_test_score": 0.04450141372147345,
      "n_estimators": 251,
      "max_depth": 6,
      "learning_rate": 0.5007152277497687,
      "subsample": 0.6951372834228112,
      "colsample_bytree": 0.39008737795130866,
      "reg_alpha": 0.7652890493236134,
      "reg_lambda": 1.0397242502752682,
      "min_child_weight": 9,
      "gamma": 0.3690110258834056
    },
    {
      "mean_test_score": 0.5426111924776618,
      "std_test_score": 0.03682321141702543,
      "n_estimators": 287,
      "max_depth": 8,
      "learning_rate": 0.5544425761292493,
      "subsample": 0.8356179872912521,
      "colsample_bytree": 0.3961401348132107,
      "reg_alpha": 1.5848843971041289,
      "reg_lambda": 0.851196946341808,
      "min_child_weight": 9,
      "gamma": 0.4240735146176037
    }
  ]
}